fund_series_issue_audit/__init__.py
fund_series_issue_audit/asset_condition_utils.py
fund_series_issue_audit/basis.py
fund_series_issue_audit/functionals.py
fund_series_issue_audit/path_director.py
fund_series_issue_audit/portfolio_info_application.py
fund_series_issue_audit/pseudo_consts.py
fund_series_issue_audit/series_issue_audit.py
fund_series_issue_audit/audit_asset/__init__.py
fund_series_issue_audit/audit_asset/asset_vectors.py
fund_series_issue_audit/audit_date/__init__.py
fund_series_issue_audit/audit_date/date_condition_utils.py
fund_series_issue_audit/audit_filter/__init__.py
fund_series_issue_audit/audit_filter/inception_dates.py
fund_series_issue_audit/audit_filter/investors.py
fund_series_issue_audit/audit_filter/pairs.py
fund_series_issue_audit/audit_filter/utils.py
fund_series_issue_audit/audit_investor/__init__.py
fund_series_issue_audit/audit_investor/inverstors_utils.py
fund_series_issue_audit/audit_investor/investors_loader.py
fund_series_issue_audit/audit_portfolio/__init__.py
fund_series_issue_audit/audit_portfolio/portfolio_vector.py
fund_series_issue_audit/audit_portfolio/vector_pair.py
fund_series_issue_audit/audit_postprocess/__init__.py
fund_series_issue_audit/audit_postprocess/post_filter.py
fund_series_issue_audit/audit_result/__init__.py
fund_series_issue_audit/audit_result/full_audit.py
fund_series_issue_audit/audit_result/full_audit_utils.py
fund_series_issue_audit/audit_result/result_application.py
fund_series_issue_audit/audit_result/result_utils.py
fund_series_issue_audit-0.3.3.data/data/requirements.txt
fund_series_issue_audit-0.3.3.dist-info/METADATA
fund_series_issue_audit-0.3.3.dist-info/WHEEL
fund_series_issue_audit-0.3.3.dist-info/top_level.txt
fund_series_issue_audit-0.3.3.dist-info/RECORD
