Metadata-Version: 2.4
Name: fund_series_issue_audit
Version: 0.3.3
Summary: A module for auditing and analyzing fund series issues
Author: June Young Park
Author-email: juneyoungpaak@gmail.com
Classifier: Development Status :: 3 - Alpha
Classifier: Intended Audience :: Financial and Insurance Industry
Classifier: Programming Language :: Python :: 3
Classifier: Programming Language :: Python :: 3.11
Requires-Python: >=3.11
Requires-Dist: openpyxl>=3.1.5
Requires-Dist: scipy>=1.11.0
Requires-Dist: requests>=2.31.0
Requires-Dist: tqdm
Requires-Dist: shining_pebbles>=0.5.5
Requires-Dist: canonical_transformer>=0.2.7
Requires-Dist: financial_dataset_preprocessor>=0.3.7
Requires-Dist: fund_insight_engine>=0.8.1
Dynamic: author
Dynamic: author-email
Dynamic: classifier
Dynamic: description
Dynamic: description-content-type
Dynamic: requires-dist
Dynamic: requires-python
Dynamic: summary
